{
	"taogi-app-admin":{
		"js":["/resources/scripts/app-admin.js"],
		"css":["/resources/css/app-admin.css"],
		"deps":[
			"taogi-ui-controls",
			"taogi-ui-hcard",
			"taogi-ui-tabs"
		]
	},
	"taogi-app-admin-entries":{
		"js":["/resources/scripts/app-admin-entries.js"],
		"css":["/resources/css/app-admin-entries.css"],
		"deps":[
			"taogi-app-admin",
			"taogi-ui-table"
		]
	},
	"taogi-app-admin-users":{
		"js":["/resources/scripts/app-admin-users.js"],
		"css":["/resources/css/app-admin-users.css"],
		"deps":[
			"taogi-app-admin",
			"taogi-ui-table"
		]
	},
	"taogi-app-admin-settings":{
		"js":["/resources/scripts/app-admin-settings.js"],
		"css":["/resources/css/app-admin-settings.css"],
		"deps":[
			"taogi-app-admin"
		]
	},

	"taogi-app-create":{
		"js":["/resources/scripts/app-entry-create.js"],
		"css":["/resources/css/app-entry-create.css"],
		"deps":[
			"jquery-ui",
			"datetimepicker",
			"caret",
			"medium-editor",
			"bgrins-spectrum",
			"fancybox",
			"ace"
		]
	},
	"taogi-app-modify":{
		"js":["/resources/scripts/app-entry-modify.js"],
		"css":["/resources/css/app-entry-modify.css"],
		"deps":[
			"taogi-app-create"
		]
	},

	"taogi-app-entry":{
		"js":["/resources/scripts/app-entry.js"],
		"css":["/resources/css/app-entry.css"],
		"deps":["taogi-defaults"]
	},
	"taogi-app-entry-revisions":{
		"js":["/resources/scripts/app-entry-revisions.js"],
		"css":["/resources/css/app-entry-revisions.css"],
		"deps":[
			"taogi-app-entry",
			"taogi-ui-controls",
			"taogi-ui-tabs",
			"taogi-ui-table"
		]
	},
	"taogi-app-entry-authors":{
		"js":["/resources/scripts/app-entry-authors.js"],
		"css":["/resources/css/app-entry-authors.css"],
		"deps":[
			"lib-tinymce",
			"taogi-ui-controls",
			"taogi-ui-tabs",
			"taogi-ui-gallery",
			"taogi-ui-table",
			"taogi-ui-forms"
			"taogi-app-entry",
		]
	},

	"taogi-app-front":{
		"js":["/resources/scripts/app-front.js"],
		"css":["/resources/css/app-front.css"],
		"deps":["taogi-ui-gallery"]
	},

	"taogi-app-login":{
		"js":["/resources/scripts/app-login.js"],
		"css":["/resources/css/app-login.css"],
		"deps":["taogi-ui-init"]
	},

	"taogi-app-regist":{
		"js":["/resources/scripts/app-regist.js"],
		"css":["/resources/css/app-regist.css"],
		"deps":["taogi-ui-forms"]
	},

	"taogi-app-user":{
		"js":["/resources/scripts/app-user.js"],
		"css":["/resources/css/app-user.css"],
		"deps":[
			"taogi-ui-hcard"
		]
	},
	"taogi-app-user-archives":{
		"js":["/resources/scripts/app-user-archives.js"],
		"css":["/resources/css/app-user-archives.css"],
		"deps":[
			"taogi-app-user",
			"taogi-ui-controls",
			"taogi-ui-tabs",
			"taogi-ui-gallery",
			"taogi-ui-table"
		]
	},
	"taogi-app-user-profile":{
		"js":["/resources/scripts/app-user-profile.js"],
		"css":["/resources/css/app-user-profile.css"],
		"deps":[
			"cropper",
			"fancybox",
			"jquery.actual",
			"jquery-file-upload",
			"lib-tinymce",
			"taogi-ui-forms",
			"taogi-ui-image-controller",
			"taogi-app-user"
		]
	}
}
